k8s_speak.py
k8s_speak-1.0.0.dist-info/licenses/LICENSE
k8s_speak-1.0.0.dist-info/METADATA
k8s_speak-1.0.0.dist-info/WHEEL
k8s_speak-1.0.0.dist-info/entry_points.txt
k8s_speak-1.0.0.dist-info/top_level.txt
k8s_speak-1.0.0.dist-info/RECORD
